[
  {
    "packageId": "com.coloros.appmanager",
    "oem": true,
    "description": "",
    "dependencies": null,
    "neededBy": null,
    "labels": null
  },
  {
    "packageId": "com.coloros.assistantscreen",
    "oem": true,
    "description": "",
    "dependencies": null,
    "neededBy": null,
    "labels": null
  },
  {
    "packageId": "com.coloros.backuprestore",
    "oem": true,
    "description": "Most likely Oppo backup/restore feature \n",
    "dependencies": null,
    "neededBy": null,
    "labels": null
  },
  {
    "packageId": "com.coloros.childrenspace",
    "oem": true,
    "description": "",
    "dependencies": null,
    "neededBy": null,
    "labels": null
  },
  {
    "packageId": "com.coloros.cloud",
    "oem": true,
    "description": "Oppo Cloud\n",
    "dependencies": null,
    "neededBy": null,
    "labels": null
  },
  {
    "packageId": "com.coloros.directui",
    "oem": true,
    "description": "",
    "dependencies": null,
    "neededBy": null,
    "labels": null
  },
  {
    "packageId": "com.coloros.findmyphone",
    "oem": true,
    "description": "Find my phone service\n",
    "dependencies": null,
    "neededBy": null,
    "labels": null
  },
  {
    "packageId": "com.coloros.gamespace",
    "oem": true,
    "description": "Game Space\nHub for your Games + some performance optimizations\nhttps://community.coloros.com/thread-9962-1-1.html\n",
    "dependencies": null,
    "neededBy": null,
    "labels": null
  },
  {
    "packageId": "com.coloros.healthcheck",
    "oem": true,
    "description": "",
    "dependencies": null,
    "neededBy": null,
    "labels": null
  },
  {
    "packageId": "com.coloros.mcs",
    "oem": true,
    "description": "",
    "dependencies": null,
    "neededBy": null,
    "labels": null
  },
  {
    "packageId": "com.coloros.ocrscanner",
    "oem": true,
    "description": "ColorOS Optical character recognition scanner\n",
    "dependencies": null,
    "neededBy": null,
    "labels": null
  },
  {
    "packageId": "com.coloros.oppomultiapp",
    "oem": true,
    "description": "",
    "dependencies": null,
    "neededBy": null,
    "labels": null
  },
  {
    "packageId": "com.coloros.phonenoareainquire",
    "oem": true,
    "description": "Number Origin\n",
    "dependencies": null,
    "neededBy": null,
    "labels": null
  },
  {
    "packageId": "com.coloros.smartdrive",
    "oem": true,
    "description": "",
    "dependencies": null,
    "neededBy": null,
    "labels": null
  },
  {
    "packageId": "com.coloros.soundrecorder",
    "oem": true,
    "description": "ColorOS Sound Recorder\n",
    "dependencies": null,
    "neededBy": null,
    "labels": null
  },
  {
    "packageId": "com.coloros.speechassist",
    "oem": true,
    "description": "ColorOS Speech Assistant\n",
    "dependencies": null,
    "neededBy": null,
    "labels": null
  },
  {
    "packageId": "com.coloros.widget.smallweather",
    "oem": true,
    "description": "",
    "dependencies": null,
    "neededBy": null,
    "labels": null
  },
  {
    "packageId": "com.coloros.widget.smallweather",
    "oem": true,
    "description": "",
    "dependencies": null,
    "neededBy": null,
    "labels": null
  },
  {
    "packageId": "com.heytap.cloud",
    "oem": true,
    "description": "HeyTap Cloud\n",
    "dependencies": null,
    "neededBy": null,
    "labels": null
  },
  {
    "packageId": "com.mobiletools.systemhelper",
    "oem": true,
    "description": "System Helper\n",
    "dependencies": null,
    "neededBy": null,
    "labels": null
  },
  {
    "packageId": "com.nearme.atlas",
    "oem": true,
    "description": "Secure payment\n",
    "dependencies": null,
    "neededBy": null,
    "labels": null
  },
  {
    "packageId": "com.nearme.browser",
    "oem": true,
    "description": "Default web browser\n",
    "dependencies": null,
    "neededBy": null,
    "labels": null
  },
  {
    "packageId": "com.nearme.instant.platform",
    "oem": true,
    "description": "",
    "dependencies": null,
    "neededBy": null,
    "labels": null
  },
  {
    "packageId": "com.nearme.themestore",
    "oem": true,
    "description": "Themes store\n",
    "dependencies": null,
    "neededBy": null,
    "labels": null
  },
  {
    "packageId": "com.oppo.fingerprints.fingerprintsensortest",
    "oem": true,
    "description": "Fingerprint sensort test\n",
    "dependencies": null,
    "neededBy": null,
    "labels": null
  },
  {
    "packageId": "com.oppo.logkitservice",
    "oem": true,
    "description": "",
    "dependencies": null,
    "neededBy": null,
    "labels": null
  },
  {
    "packageId": "com.oppo.logkit",
    "oem": true,
    "description": "",
    "dependencies": null,
    "neededBy": null,
    "labels": null
  },
  {
    "packageId": "com.oppo.market",
    "oem": true,
    "description": "Oppo App Market\n",
    "dependencies": null,
    "neededBy": null,
    "labels": null
  },
  {
    "packageId": "com.oppo.music",
    "oem": true,
    "description": "Oppo Music app\n",
    "dependencies": null,
    "neededBy": null,
    "labels": null
  },
  {
    "packageId": "com.oppo.ovoicemanager",
    "oem": true,
    "description": "",
    "dependencies": null,
    "neededBy": null,
    "labels": null
  },
  {
    "packageId": "com.oppo.oppopowermonitor",
    "oem": true,
    "description": "",
    "dependencies": null,
    "neededBy": null,
    "labels": null
  },
  {
    "packageId": "com.oppo.quicksearchbox",
    "oem": true,
    "description": "Single swip from top to bottom search that has lots of Chinese in it\n",
    "dependencies": null,
    "neededBy": null,
    "labels": null
  },
  {
    "packageId": "com.oppo.securepay",
    "oem": true,
    "description": "Payment Protection\n",
    "dependencies": null,
    "neededBy": null,
    "labels": null
  },
  {
    "packageId": "com.coloros.wallet",
    "oem": true,
    "description": "Oppo Wallet\n",
    "dependencies": null,
    "neededBy": null,
    "labels": null
  },
  {
    "packageId": "com.realme.findphone.client2",
    "oem": true,
    "description": "Find my phone client app\n",
    "dependencies": null,
    "neededBy": null,
    "labels": null
  },
  {
    "packageId": "com.coloros.filemanager",
    "oem": true,
    "description": "ColorOS File Manager\n",
    "dependencies": null,
    "neededBy": null,
    "labels": null
  },
  {
    "packageId": "com.coloros.pictorial(LockscreenMagazine)",
    "oem": true,
    "description": "Removal will result in no longer being able to access Lockscreen settings.\n",
    "dependencies": null,
    "neededBy": null,
    "labels": null
  },
  {
    "packageId": "com.coloros.securitypermission",
    "oem": true,
    "description": "Handles app permission management. DO NOT REMOVE THIS\n",
    "dependencies": null,
    "neededBy": null,
    "labels": null
  },
  {
    "packageId": "com.oppo.freefallingmonitor",
    "oem": true,
    "description": "Provides protection for camera slider in the event of a fall. \nBest described here: https://www.gizchina.com/2018/06/20/oppo-find-x-slide-up-camera-has-anti-fall-feature-guarantees-5-years-usage/\n",
    "dependencies": null,
    "neededBy": null,
    "labels": null
  },
  {
    "packageId": "com.oppo.webview",
    "oem": true,
    "description": "Oppo Webview\nA WebView is a system component for the Android operating system (OS) that allows Android apps to display content \nfrom the web directly inside an application. It's based on Chrome.\nOn open-source privacy oriented Webview is Bromite (https://www.bromite.org/system_web_view)\n",
    "dependencies": null,
    "neededBy": null,
    "labels": null
  },
  {
    "packageId": "com.sohu.inputmethod.sogouoem",
    "oem": true,
    "description": "Default keyboard\n",
    "dependencies": null,
    "neededBy": null,
    "labels": null
  }
]